hufr/__init__.py
hufr/constants.py
hufr/convert.py
hufr/models/__init__.py
hufr/models/ner.py
hufr/models/onnx.py
hufr/models/utils.py
hufr/onnx.py
hufr/redact.py
hufr/utils.py
hufr-2.0.1.dist-info/LICENSE
hufr-2.0.1.dist-info/METADATA
hufr-2.0.1.dist-info/WHEEL
hufr-2.0.1.dist-info/RECORD
