Metadata-Version: 2.1
Name: hufr
Version: 2.0.1
Summary: Redact Text with HuggingFace Models
Home-page: https://github.com/robertsonwang/hufr
License: Apache 2.0
Keywords: huggingface,pii,ner,ONNX,NLP,redactions
Author: Robertson Wang
Author-email: robertsonwang@gmail.com
Requires-Python: >=3.9,<4.0
Classifier: License :: Other/Proprietary License
Classifier: Programming Language :: Python :: 3
Classifier: Programming Language :: Python :: 3.9
Classifier: Programming Language :: Python :: 3.10
Classifier: Programming Language :: Python :: 3.11
Classifier: Programming Language :: Python :: 3.12
Provides-Extra: cpu
Provides-Extra: gpu
Requires-Dist: onnx (>=1.15.0,<2.0.0)
Requires-Dist: onnxruntime (>=1.13.1,<2.0.0) ; extra != "gpu"
Requires-Dist: onnxruntime-gpu (>=1.13.1,<2.0.0) ; extra == "gpu"
Requires-Dist: torch (>=2.1.2,<3.0.0)
Requires-Dist: transformers (>=4.36.2,<4.37.0)
Project-URL: Repository, https://github.com/robertsonwang/hufr
